secretarium_connector/__init__.py
secretarium_connector/key.py
secretarium_connector/utils.py
typings/asn1crypto/__init__.pyi
typings/asn1crypto/_errors.pyi
typings/asn1crypto/_inet.pyi
typings/asn1crypto/_iri.pyi
typings/asn1crypto/_ordereddict.pyi
typings/asn1crypto/_teletex_codec.pyi
typings/asn1crypto/_types.pyi
typings/asn1crypto/core.pyi
typings/asn1crypto/parser.pyi
typings/asn1crypto/util.pyi
typings/asn1crypto/version.pyi
secretarium_connector-0.0.7.dist-info/METADATA
secretarium_connector-0.0.7.dist-info/WHEEL
secretarium_connector-0.0.7.dist-info/top_level.txt
secretarium_connector-0.0.7.dist-info/RECORD
